kdtree/__init__.py
kdtree/node.py
kdtree/region.py
kdtree/tree.py
kdtree_python-0.2.2.dist-info/LICENSE
kdtree_python-0.2.2.dist-info/METADATA
kdtree_python-0.2.2.dist-info/WHEEL
kdtree_python-0.2.2.dist-info/top_level.txt
kdtree_python-0.2.2.dist-info/RECORD
