Metadata-Version: 2.1
Name: kdtree-python
Version: 0.2.2
Summary: Implementation of a multidimensional binary search tree for associative searching
Home-page: https://github.com/alesanfra/kdtree
Author: Alessio Sanfratello
License: UNKNOWN
Platform: UNKNOWN
Classifier: Programming Language :: Python :: 3
Classifier: Operating System :: OS Independent
Classifier: Topic :: Software Development :: Libraries
Classifier: Topic :: Utilities
Classifier: Intended Audience :: Science/Research
Requires-Python: >=3.6
